face_recognition/__init__.py
face_recognition/api.py
face_recognition/cli.py
friday_face_recognition-1.0.0.dist-info/DESCRIPTION.rst
friday_face_recognition-1.0.0.dist-info/METADATA
friday_face_recognition-1.0.0.dist-info/RECORD
friday_face_recognition-1.0.0.dist-info/WHEEL
friday_face_recognition-1.0.0.dist-info/entry_points.txt
friday_face_recognition-1.0.0.dist-info/metadata.json
friday_face_recognition-1.0.0.dist-info/top_level.txt
